README.md
setup.py
bin/pygeek-stellar
pygeek_stellar/__init__.py
pygeek_stellar/cli_session.py
pygeek_stellar/constants.py
pygeek_stellar/geek_stellar_cmd.py
pygeek_stellar/pygeek_stellar.py
pygeek_stellar/stellar_operations.py
pygeek_stellar/stellar_queries.py
pygeek_stellar/stellar_requests.py
pygeek_stellar.egg-info/PKG-INFO
pygeek_stellar.egg-info/SOURCES.txt
pygeek_stellar.egg-info/dependency_links.txt
pygeek_stellar.egg-info/not-zip-safe
pygeek_stellar.egg-info/requires.txt
pygeek_stellar.egg-info/top_level.txt
pygeek_stellar/utils/cryptography.py
pygeek_stellar/utils/file.py
pygeek_stellar/utils/generic.py
pygeek_stellar/utils/stellar.py
pygeek_stellar/utils/user_input.py