Metadata-Version: 1.2
Name: pygeek-stellar
Version: 0.2
Summary: A Python CLI to interact with the Stellar network.
Home-page: https://github.com/XavierAraujo/pygeek-stellar
Author: Xavier Araújo
Author-email: xavier.araujo92@gmail.com
License: MIT
Platform: UNKNOWN
Requires-Python: >=3.7
